{
    "Raw": {
        "Entity": {
            "Category": "Default",
            "Icon": "Default.bmp",
            "Invisible": 0,
            "BBoxSelection": 0,
            "entityDensityClass": "ad1a0441-246c-4b7a-859d-bfa38f91a816",
            "__ref": "9b8d6f07-8eb2-4760-a62f-72b363169aec",
            "__path": "libs/foundry/records/entities/scitem/carryables/1h/carryable_1h_sq_datapad_fluff_orb_genericgang_003.xml",
            "defaultEditorColor": {
                "r": 1,
                "g": 1,
                "b": 0
            },
            "tags": [
                {
                    "value": "5e11a544-7fea-4160-b2bf-98c6cf9ee9df"
                },
                {
                    "value": "00ead468-9073-485b-a6df-ca6b94053603"
                },
                {
                    "value": "4def30aa-4ed2-404a-9439-6713f246f1e3"
                },
                {
                    "value": "05e263e6-d3be-40dd-a89d-6ff7d1d8a3ac"
                }
            ],
            "Components": {
                "SEntityPhysicsControllerParams": {
                    "PhysType": {
                        "SEntityRigidPhysicsControllerParams": {
                            "Mass": 0.25,
                            "compoundingAllowed": 1,
                            "spawnBoxScale": 0.5,
                            "maxLoggedCollisions": 1,
                            "Damping": 0.01,
                            "DampingZeroG": 0.01,
                            "DampingFreefall": 0.05,
                            "PushableByPlayers": 1,
                            "NeverAffectTriggers": 0,
                            "UseManualGridTransition": 0,
                            "aiNavigationType": "Included",
                            "Kinematic": 0,
                            "EnableCrossGridChecks": 0,
                            "Resting": 0,
                            "physicalizeAllSlots": 1,
                            "enableExteriorShadow": 0,
                            "temperature": {
                                "enable": 0,
                                "initialTemperature": -1,
                                "internalTemperatureGeneration": 0,
                                "coolingEqualizationParams": {
                                    "CoolingEqualizationMultiplier": {
                                        "coolingEqualizationMultiplier": 1
                                    }
                                },
                                "signatureParams": {
                                    "enable": 0,
                                    "minimumTemperatureForIR": 250,
                                    "temperatureToIR": 6
                                },
                                "itemResourceParams": {
                                    "poweredAmbientCoolingMultiplier": 1,
                                    "minOperatingTemperature": 0,
                                    "minCoolingTemperature": 300,
                                    "enableOverheat": 0,
                                    "overheatTemperature": 450,
                                    "overheatWarningTemperature": 370,
                                    "overheatRecoveryTemperature": 350
                                },
                                "misfireTemperatureRange": {
                                    "minimum": 370,
                                    "maximum": 600
                                },
                                "fireHazard": {
                                    "enable": 1,
                                    "dissolveOnBurn": 0,
                                    "dissolvePercentageRange": {
                                        "minimum": 0,
                                        "maximum": 1
                                    }
                                }
                            }
                        }
                    }
                },
                "SAttachableComponentParams": {
                    "attachToTileItemPort": "NoConnection",
                    "AttachDef": {
                        "Type": "Misc",
                        "SubType": "UNDEFINED",
                        "Size": 1,
                        "Grade": 1,
                        "inheritParentManufacturer": 0,
                        "Tags": "Tablet",
                        "ignoredAttachAxis": "None",
                        "attachCheckCenterOfMass": 0,
                        "Localization": {
                            "Name": "<= PLACEHOLDER =>",
                            "__Name": "@LOC_PLACEHOLDER",
                            "ShortName": "",
                            "__ShortName": "@LOC_EMPTY",
                            "Description": "",
                            "__Description": "@LOC_EMPTY",
                            "displayFeatures": {
                                "History": "",
                                "__History": "@LOC_EMPTY",
                                "Callout1": "",
                                "__Callout1": "@LOC_EMPTY",
                                "Callout2": "",
                                "__Callout2": "@LOC_EMPTY",
                                "Callout3": "",
                                "__Callout3": "@LOC_EMPTY",
                                "UIPriority": 0
                            },
                            "English": {
                                "Locale": "english",
                                "Name": "<= PLACEHOLDER =>",
                                "ShortName": "",
                                "Description": ""
                            }
                        },
                        "mannequinTags": {
                            "mannequinTypeTag": "Tablet"
                        },
                        "inventoryOccupancyVolume": {
                            "SMicroCargoUnit": {
                                "microSCU": 1200
                            }
                        },
                        "inventoryOccupancyDimensions": {
                            "x": 0.2498,
                            "y": 0.3017,
                            "z": 0.0204
                        },
                        "inventoryOccupancyLocalBoundsMin": {
                            "x": -0.125,
                            "y": -0.161,
                            "z": -0.001
                        },
                        "inventoryOccupancyLocalBoundsMax": {
                            "x": 0.137,
                            "y": 0.161,
                            "z": 0.016
                        },
                        "inventoryOccupancyDimensionsUIOverride": {
                            "Vec3": {
                                "x": 0.75,
                                "y": 0.75,
                                "z": 0.75
                            }
                        }
                    }
                },
                "SEntityComponentCarryableParams": {
                    "interactionMetadata": "ea5b5582-1723-4e0d-80ea-a2b546d21302",
                    "canBeCarriedInProne": 1,
                    "disableRotation": 0,
                    "carryInteraction": {
                        "value": "SSharedInteractionParams[E116]"
                    },
                    "placeInteraction": {
                        "value": "SSharedInteractionParams[E119]"
                    },
                    "dropInteraction": {
                        "value": "SSharedInteractionParams[E117]"
                    },
                    "storeInteraction": {
                        "value": "SSharedInteractionParams[E11A]"
                    },
                    "inspectInteraction": {
                        "value": "SSharedInteractionParams[E118]"
                    },
                    "carryableStatesParams": {
                        "settledState": {
                            "value": "SInteractionState[9A35]"
                        },
                        "carriedState": {
                            "value": "SInteractionState[9A36]"
                        },
                        "equippedToSuitState": {
                            "value": "SInteractionState[9A37]"
                        },
                        "inspectingState": {
                            "value": "SInteractionState[9A38]"
                        },
                        "droppedState": {
                            "value": "SInteractionState[9A39]"
                        },
                        "offeredState": {
                            "value": "SInteractionState[9A3A]"
                        },
                        "storedState": {
                            "value": "SInteractionState[9A3B]"
                        }
                    },
                    "interactionPointOffsets": {
                        "interactionOffsetEquipped": {
                            "Rotation": {
                                "x": 0,
                                "y": 0,
                                "z": 0
                            },
                            "Position": {
                                "x": 0,
                                "y": 0,
                                "z": 0
                            }
                        },
                        "interactionOffsetCarried": {
                            "Rotation": {
                                "x": 0,
                                "y": 0,
                                "z": 0
                            },
                            "Position": {
                                "x": 0,
                                "y": 0,
                                "z": 0
                            }
                        },
                        "interactionOffsetInspected": {
                            "Rotation": {
                                "x": 0,
                                "y": 0,
                                "z": 0
                            },
                            "Position": {
                                "x": 0,
                                "y": 0,
                                "z": 0
                            }
                        }
                    },
                    "gripData": {
                        "gripOverrideUsingLOS": 0,
                        "grips": [
                            {
                                "carryStyleID": "1H_Standard",
                                "canBeUsedBy": "All",
                                "handMode": "RightHand",
                                "gripAction": "None",
                                "handGrip": {
                                    "optionalHelper": "$grip_right_1",
                                    "gripShapeParameters": {
                                        "gripShape": "gs_square",
                                        "dimension": 0.7,
                                        "wristRotation": 0
                                    },
                                    "offset": {
                                        "Rotation": {
                                            "x": 0,
                                            "y": 0,
                                            "z": 0
                                        },
                                        "Position": {
                                            "x": 0,
                                            "y": 0,
                                            "z": 0
                                        }
                                    }
                                },
                                "animationParameters": {
                                    "motionBase": "1hr"
                                },
                                "carryParameters": {
                                    "width": 0,
                                    "height": 0,
                                    "depth": 0
                                }
                            },
                            {
                                "carryStyleID": "1H_Standard",
                                "canBeUsedBy": "All",
                                "handMode": "LeftHand",
                                "gripAction": "None",
                                "handGrip": {
                                    "optionalHelper": "$grip_left_1",
                                    "gripShapeParameters": {
                                        "gripShape": "gs_none",
                                        "dimension": 0,
                                        "wristRotation": 0
                                    },
                                    "offset": {
                                        "Rotation": {
                                            "x": 0,
                                            "y": 0,
                                            "z": 0
                                        },
                                        "Position": {
                                            "x": 0,
                                            "y": 0,
                                            "z": 0
                                        }
                                    }
                                },
                                "animationParameters": {
                                    "motionBase": "1hl"
                                },
                                "carryParameters": {
                                    "width": 0,
                                    "height": 0,
                                    "depth": 0
                                }
                            }
                        ]
                    },
                    "carryableTasks": {
                        "SSequencerSetInteractionStateCarryableTaskParams": {
                            "state": {
                                "value": "SInteractionState[9A38]"
                            }
                        }
                    },
                    "throwableParams": {
                        "reticle": "none",
                        "faceUpWhenSettled": 1,
                        "allowHologramTiltRotation": 0,
                        "placementRange": 3,
                        "placementRangeHysteresis": 0.5,
                        "yawOffset": 0,
                        "applyBoundingBoxPlacementOffset": 0,
                        "combatThrowable": 0,
                        "knockdownThrowUpForce": 0.5,
                        "throwModes": [
                            {
                                "mode": "Drop",
                                "angularVelocity": {
                                    "x": 0,
                                    "y": 0,
                                    "z": 1
                                },
                                "offset": {
                                    "x": 0,
                                    "y": 0,
                                    "z": 0
                                }
                            },
                            {
                                "mode": "OverhandThrow",
                                "angularVelocity": {
                                    "x": 0,
                                    "y": 0,
                                    "z": 1
                                },
                                "offset": {
                                    "x": 0,
                                    "y": 0,
                                    "z": 0
                                }
                            },
                            {
                                "mode": "UnderhandThrow",
                                "angularVelocity": {
                                    "x": 0,
                                    "y": 0,
                                    "z": 0
                                },
                                "offset": {
                                    "x": 0,
                                    "y": 0,
                                    "z": 0
                                }
                            },
                            {
                                "mode": "Place",
                                "angularVelocity": {
                                    "x": 0,
                                    "y": 0,
                                    "z": 0
                                },
                                "offset": {
                                    "x": 0,
                                    "y": 0,
                                    "z": 0
                                }
                            },
                            {
                                "mode": "InteractionMode",
                                "angularVelocity": {
                                    "x": 0,
                                    "y": 0,
                                    "z": 0
                                },
                                "offset": {
                                    "x": 0,
                                    "y": 0,
                                    "z": 0
                                }
                            }
                        ],
                        "audioParams": {
                            "onCollisionAudioPerceptionInfo": "SmallSound",
                            "onCollisionAudioPerceptionRadius": 20
                        },
                        "defaultPlacementUpDirection": {
                            "x": 0,
                            "y": 0,
                            "z": 1
                        }
                    }
                },
                "SEntityInteractableParams": {
                    "Interactable": {
                        "SharedInteractions": [
                            {
                                "Name": "Carry",
                                "DisplayName": "Carry",
                                "__DisplayName": "@interaction_carry",
                                "DisplayType": "Show",
                                "GenericCursor": "Grab",
                                "FocusModeOnly": 0,
                                "Sendable": 0,
                                "Linkable": 0,
                                "LockedByLinks": 0,
                                "RequiresAuthorizedUser": 0,
                                "available": 1,
                                "InheritsConditionDisplaysThroughLinks": 0,
                                "conditionList": {
                                    "InteractionConditionList": {
                                        "presetList": {
                                            "Reference": {
                                                "value": "cfbf64fc-515a-4777-835d-4328af0d3003"
                                            }
                                        }
                                    }
                                }
                            },
                            {
                                "Name": "Drop",
                                "DisplayName": "Drop",
                                "__DisplayName": "@interaction_drop",
                                "DisplayType": "Show",
                                "GenericCursor": "SingleAction",
                                "FocusModeOnly": 0,
                                "Sendable": 0,
                                "Linkable": 0,
                                "LockedByLinks": 0,
                                "RequiresAuthorizedUser": 0,
                                "available": 1,
                                "InheritsConditionDisplaysThroughLinks": 0,
                                "conditionList": {
                                    "InteractionConditionList": {
                                        "presetList": {
                                            "Reference": {
                                                "value": "901b0193-5e7c-4a9b-9dc6-0a5af5420e51"
                                            }
                                        }
                                    }
                                }
                            },
                            {
                                "Name": "Inspect",
                                "DisplayName": "Inspect",
                                "__DisplayName": "@innerthought_inspect",
                                "DisplayType": "Show",
                                "GenericCursor": "SingleAction",
                                "FocusModeOnly": 0,
                                "Sendable": 0,
                                "Linkable": 0,
                                "LockedByLinks": 0,
                                "RequiresAuthorizedUser": 0,
                                "available": 1,
                                "InheritsConditionDisplaysThroughLinks": 0,
                                "conditionList": {
                                    "InteractionConditionList": {
                                        "presetList": {
                                            "Reference": {
                                                "value": "2f90a95d-d090-447b-9620-125f31599e2c"
                                            }
                                        }
                                    }
                                }
                            },
                            {
                                "Name": "Place",
                                "DisplayName": "Place",
                                "__DisplayName": "@interaction_place",
                                "DisplayType": "Show",
                                "GenericCursor": "SingleAction",
                                "FocusModeOnly": 0,
                                "Sendable": 0,
                                "Linkable": 0,
                                "LockedByLinks": 0,
                                "RequiresAuthorizedUser": 0,
                                "available": 1,
                                "InheritsConditionDisplaysThroughLinks": 0,
                                "conditionList": {
                                    "InteractionConditionList": {
                                        "presetList": {
                                            "Reference": {
                                                "value": "9e196f93-d77e-4d6e-80b4-2378dcbbf0bf"
                                            }
                                        }
                                    }
                                }
                            },
                            {
                                "Name": "Store",
                                "DisplayName": "Store",
                                "__DisplayName": "@interaction_store",
                                "DisplayType": "Show",
                                "GenericCursor": "SingleAction",
                                "FocusModeOnly": 0,
                                "Sendable": 0,
                                "Linkable": 0,
                                "LockedByLinks": 0,
                                "RequiresAuthorizedUser": 0,
                                "available": 1,
                                "InheritsConditionDisplaysThroughLinks": 0,
                                "conditionList": {
                                    "InteractionConditionList": {
                                        "presetList": {
                                            "Reference": {
                                                "value": "29323715-dae3-41f0-8680-07aa4307e9ca"
                                            }
                                        }
                                    }
                                }
                            },
                            {
                                "Name": "Drink",
                                "DisplayName": "Drink",
                                "__DisplayName": "@interaction_drink",
                                "DisplayType": "Show",
                                "GenericCursor": "SingleAction",
                                "FocusModeOnly": 0,
                                "Sendable": 0,
                                "Linkable": 0,
                                "LockedByLinks": 0,
                                "RequiresAuthorizedUser": 0,
                                "available": 1,
                                "InheritsConditionDisplaysThroughLinks": 0
                            }
                        ],
                        "InteractionPoints": {
                            "SInteractionPointParams": {
                                "FirstInteractionPrimary": 0,
                                "UseHelperLocation": 0,
                                "ApplyToEntireSkeleton": 1,
                                "longRangeIP": 0,
                                "Radius": 2,
                                "ShowHighlight": 1,
                                "HighlightOnRayHitEntity": 1,
                                "TextJustification": "Middle",
                                "TextOrientation": "RotateToPlayer",
                                "TextScale": 1,
                                "ShowInteractionTextAtCursorPos": 0,
                                "ScalePromptOffsetWithEntity": 0,
                                "PromptStyle": "PromptAndText",
                                "OverrideControlHintDescription": 0,
                                "InteractionPromptScale": 1,
                                "InteractionPromptLabelVerticalOffset": 70,
                                "InteractionPromptBound": "TopBoundingBoxZSurface",
                                "UseHorizontalDistance": 0,
                                "MaxCursorScreenDistance": 2,
                                "ShowInnerThoughtsOffScreen": 0,
                                "OnlySelectableInLookDir": 0,
                                "Interactions": [
                                    {
                                        "DisplayName": "",
                                        "__DisplayName": "@LOC_EMPTY",
                                        "IsPrimary": 0,
                                        "Interaction": {
                                            "value": "SSharedInteractionParams[E2A5]"
                                        }
                                    },
                                    {
                                        "DisplayName": "",
                                        "__DisplayName": "@LOC_EMPTY",
                                        "IsPrimary": 0,
                                        "Interaction": {
                                            "value": "SSharedInteractionParams[E2A6]"
                                        }
                                    },
                                    {
                                        "DisplayName": "",
                                        "__DisplayName": "@LOC_EMPTY",
                                        "IsPrimary": 0,
                                        "Interaction": {
                                            "value": "SSharedInteractionParams[E2AA]"
                                        }
                                    },
                                    {
                                        "DisplayName": "",
                                        "__DisplayName": "@LOC_EMPTY",
                                        "IsPrimary": 0,
                                        "Interaction": {
                                            "value": "SSharedInteractionParams[E2A8]"
                                        }
                                    },
                                    {
                                        "DisplayName": "",
                                        "__DisplayName": "@LOC_EMPTY",
                                        "IsPrimary": 0,
                                        "Interaction": {
                                            "value": "SSharedInteractionParams[E2AD]"
                                        }
                                    }
                                ],
                                "Offset": {
                                    "Rotation": {
                                        "x": 0,
                                        "y": 0,
                                        "z": 0
                                    },
                                    "Position": {
                                        "x": 0,
                                        "y": 0,
                                        "z": 0
                                    }
                                },
                                "InteractionPromptOffset": {
                                    "Rotation": {
                                        "x": 0,
                                        "y": 0,
                                        "z": 0
                                    },
                                    "Position": {
                                        "x": 0,
                                        "y": 0,
                                        "z": 0
                                    }
                                },
                                "AngleConstraint": {
                                    "angleRange": 181,
                                    "viewAngleLimit": 110,
                                    "forwardDirOffset": {
                                        "x": 0,
                                        "y": 0,
                                        "z": 0
                                    }
                                }
                            }
                        }
                    }
                },
                "SGeometryResourceParams": {
                    "cacheResources": 0,
                    "rootOverridePaint": 0,
                    "inheritModelTagFromHost": 1,
                    "Geometry": {
                        "ScaleMultiplier": 1,
                        "Geometry": {
                            "Slot": "Main",
                            "AttachFlags": 0,
                            "DeformerType": "Standard",
                            "ProtosBShapeExclude": 0,
                            "VisTP": 1,
                            "VisFP": 1,
                            "VisShadow": 1,
                            "VisSecondaryViews": 1,
                            "WrinkleMap": 0,
                            "EnableDecalProjection": 0,
                            "BBoxRadius": 0,
                            "Wear": 0,
                            "Dirt": 0,
                            "Interference": 0,
                            "Damage": 0,
                            "RenderLayer": "Default",
                            "VisAreaMode": "AABB_Center",
                            "SunShadowMode": "Upto_400m",
                            "LodRatio": 100,
                            "Geometry": {
                                "path": "objects/buildingsets/human/universal/prop/tablets/datapad_tablet_2_a.cgf"
                            }
                        }
                    }
                },
                "SCItemInspectableParams": {
                    "inspectRotateScaleX": 0.025,
                    "inspectRotateScaleY": 0.025,
                    "inspectInteraction": {
                        "value": "SSharedInteractionParams[E118]"
                    },
                    "inspectRotateLimitsX": {
                        "x": -1,
                        "y": 1
                    },
                    "inspectRotateLimitsY": {
                        "x": -1,
                        "y": 1
                    },
                    "firstSelect": {
                        "firstSelectMode": "None"
                    }
                },
                "SInteractionStateMachineParams": {
                    "StateTypes": [
                        {
                            "StateTypeName": "CarryableStates",
                            "bindingsMethod": "States",
                            "asopReset": 0,
                            "networkAuthority": "Server",
                            "DefaultState": {
                                "value": "SInteractionState[9A35]"
                            },
                            "States": [
                                {
                                    "StateName": "Carried",
                                    "Interactions": [
                                        {
                                            "Interaction": {
                                                "value": "SSharedInteractionParams[A56F]"
                                            }
                                        },
                                        {
                                            "Interaction": {
                                                "value": "SSharedInteractionParams[A56E]"
                                            }
                                        },
                                        {
                                            "Interaction": {
                                                "value": "SSharedInteractionParams[A570]"
                                            }
                                        },
                                        {
                                            "Interaction": {
                                                "value": "SSharedInteractionParams[A571]"
                                            }
                                        }
                                    ],
                                    "interactionPoints": {
                                        "SInteractionPointParams": {
                                            "HelperName": "HighlightOnRayHitEntity",
                                            "FirstInteractionPrimary": 0,
                                            "UseHelperLocation": 0,
                                            "ApplyToEntireSkeleton": 0,
                                            "longRangeIP": 0,
                                            "Radius": 2,
                                            "ShowHighlight": 1,
                                            "HighlightOnRayHitEntity": 1,
                                            "TextJustification": "Middle",
                                            "TextOrientation": "RotateToPlayer",
                                            "TextScale": 1,
                                            "ShowInteractionTextAtCursorPos": 0,
                                            "ScalePromptOffsetWithEntity": 0,
                                            "PromptStyle": "PromptAndText",
                                            "OverrideControlHintDescription": 0,
                                            "InteractionPromptScale": 1,
                                            "InteractionPromptLabelVerticalOffset": 70,
                                            "InteractionPromptBound": "TopBoundingBoxZSurface",
                                            "UseHorizontalDistance": 0,
                                            "MaxCursorScreenDistance": 2,
                                            "ShowInnerThoughtsOffScreen": 0,
                                            "OnlySelectableInLookDir": 0,
                                            "Interactions": [
                                                {
                                                    "DisplayName": "",
                                                    "__DisplayName": "@LOC_EMPTY",
                                                    "IsPrimary": 1,
                                                    "Interaction": {
                                                        "value": "SSharedInteractionParams[A56D]"
                                                    }
                                                },
                                                {
                                                    "DisplayName": "",
                                                    "__DisplayName": "@LOC_EMPTY",
                                                    "IsPrimary": 0,
                                                    "Interaction": {
                                                        "value": "SSharedInteractionParams[A570]"
                                                    }
                                                },
                                                {
                                                    "DisplayName": "",
                                                    "__DisplayName": "@LOC_EMPTY",
                                                    "IsPrimary": 0,
                                                    "Interaction": {
                                                        "value": "SSharedInteractionParams[A571]"
                                                    }
                                                },
                                                {
                                                    "DisplayName": "",
                                                    "__DisplayName": "@LOC_EMPTY",
                                                    "IsPrimary": 0,
                                                    "Interaction": {
                                                        "value": "SSharedInteractionParams[A572]"
                                                    }
                                                },
                                                {
                                                    "DisplayName": "Loot",
                                                    "__DisplayName": "@interaction_loot",
                                                    "IsPrimary": 0,
                                                    "Interaction": {
                                                        "value": "SSharedInteractionParams[A573]"
                                                    }
                                                }
                                            ],
                                            "Tags": [
                                                {
                                                    "value": "c7663132-a612-4b0c-bc5b-144ac55e267e"
                                                },
                                                {
                                                    "value": "ce1c13f1-a8ba-49cf-a025-89475ea07000"
                                                }
                                            ],
                                            "Offset": {
                                                "Rotation": {
                                                    "x": 0,
                                                    "y": 0,
                                                    "z": 0
                                                },
                                                "Position": {
                                                    "x": 0,
                                                    "y": 0,
                                                    "z": 0
                                                }
                                            },
                                            "InteractionPromptOffset": {
                                                "Rotation": {
                                                    "x": 0,
                                                    "y": 0,
                                                    "z": 0
                                                },
                                                "Position": {
                                                    "x": 0,
                                                    "y": 0,
                                                    "z": 0
                                                }
                                            },
                                            "AngleConstraint": {
                                                "angleRange": 181,
                                                "viewAngleLimit": 110,
                                                "forwardDirOffset": {
                                                    "x": 0,
                                                    "y": 0,
                                                    "z": 0
                                                }
                                            }
                                        }
                                    }
                                },
                                {
                                    "StateName": "Dropped"
                                },
                                {
                                    "StateName": "Stored",
                                    "Interactions": [
                                        {
                                            "Interaction": {
                                                "value": "SSharedInteractionParams[A56D]"
                                            }
                                        },
                                        {
                                            "Interaction": {
                                                "value": "SSharedInteractionParams[A56E]"
                                            }
                                        },
                                        {
                                            "Interaction": {
                                                "value": "SSharedInteractionParams[A571]"
                                            }
                                        },
                                        {
                                            "Interaction": {
                                                "value": "SSharedInteractionParams[A572]"
                                            }
                                        }
                                    ],
                                    "interactionPoints": {
                                        "SInteractionPointParams": {
                                            "HelperName": "Spine3",
                                            "FirstInteractionPrimary": 0,
                                            "UseHelperLocation": 0,
                                            "ApplyToEntireSkeleton": 0,
                                            "longRangeIP": 0,
                                            "Radius": 2,
                                            "ShowHighlight": 1,
                                            "HighlightOnRayHitEntity": 0,
                                            "TextJustification": "Middle",
                                            "TextOrientation": "RotateToPlayer",
                                            "TextScale": 1,
                                            "ShowInteractionTextAtCursorPos": 0,
                                            "ScalePromptOffsetWithEntity": 0,
                                            "PromptStyle": "PromptAndText",
                                            "OverrideControlHintDescription": 0,
                                            "InteractionPromptScale": 1,
                                            "InteractionPromptLabelVerticalOffset": 70,
                                            "InteractionPromptBound": "EntityRoot",
                                            "UseHorizontalDistance": 0,
                                            "MaxCursorScreenDistance": 2,
                                            "ShowInnerThoughtsOffScreen": 0,
                                            "OnlySelectableInLookDir": 0,
                                            "Interactions": [
                                                {
                                                    "DisplayName": "",
                                                    "__DisplayName": "@LOC_EMPTY",
                                                    "IsPrimary": 0,
                                                    "Interaction": {
                                                        "value": "SSharedInteractionParams[A56D]"
                                                    }
                                                },
                                                {
                                                    "DisplayName": "",
                                                    "__DisplayName": "@LOC_EMPTY",
                                                    "IsPrimary": 0,
                                                    "Interaction": {
                                                        "value": "SSharedInteractionParams[A56E]"
                                                    }
                                                },
                                                {
                                                    "DisplayName": "",
                                                    "__DisplayName": "@LOC_EMPTY",
                                                    "IsPrimary": 0,
                                                    "Interaction": {
                                                        "value": "SSharedInteractionParams[A56F]"
                                                    }
                                                },
                                                {
                                                    "DisplayName": "",
                                                    "__DisplayName": "@LOC_EMPTY",
                                                    "IsPrimary": 0,
                                                    "Interaction": {
                                                        "value": "SSharedInteractionParams[A570]"
                                                    }
                                                },
                                                {
                                                    "DisplayName": "",
                                                    "__DisplayName": "@LOC_EMPTY",
                                                    "IsPrimary": 0,
                                                    "Interaction": {
                                                        "value": "SSharedInteractionParams[A571]"
                                                    }
                                                },
                                                {
                                                    "DisplayName": "Open",
                                                    "__DisplayName": "@interaction_open",
                                                    "IsPrimary": 0,
                                                    "Interaction": {
                                                        "value": "SSharedInteractionParams[A572]"
                                                    }
                                                },
                                                {
                                                    "DisplayName": "Loot",
                                                    "__DisplayName": "@interaction_loot",
                                                    "IsPrimary": 0,
                                                    "Interaction": {
                                                        "value": "SSharedInteractionParams[A573]"
                                                    }
                                                }
                                            ],
                                            "Tags": [
                                                {
                                                    "value": "95b959c6-fb00-4d63-b062-a36d86b66128"
                                                },
                                                {
                                                    "value": "d8a79162-cc7b-4f0d-9445-c25530cf1588"
                                                }
                                            ],
                                            "Offset": {
                                                "Rotation": {
                                                    "x": 0,
                                                    "y": 0,
                                                    "z": 0
                                                },
                                                "Position": {
                                                    "x": 0,
                                                    "y": 0,
                                                    "z": 0
                                                }
                                            },
                                            "InteractionPromptOffset": {
                                                "Rotation": {
                                                    "x": 0,
                                                    "y": 0,
                                                    "z": 0
                                                },
                                                "Position": {
                                                    "x": 0,
                                                    "y": 0,
                                                    "z": 0
                                                }
                                            },
                                            "AngleConstraint": {
                                                "angleRange": 181,
                                                "viewAngleLimit": 110,
                                                "forwardDirOffset": {
                                                    "x": 0,
                                                    "y": 0,
                                                    "z": 0
                                                }
                                            }
                                        }
                                    }
                                },
                                {
                                    "StateName": "EquippedWorn"
                                },
                                {
                                    "StateName": "HangingOnOutfitHanger",
                                    "interactionPoints": {
                                        "SInteractionPointParams": {
                                            "HelperName": "HighlightOnRayHitEntity",
                                            "FirstInteractionPrimary": 0,
                                            "UseHelperLocation": 0,
                                            "ApplyToEntireSkeleton": 0,
                                            "longRangeIP": 0,
                                            "Radius": 2,
                                            "ShowHighlight": 1,
                                            "HighlightOnRayHitEntity": 1,
                                            "TextJustification": "Middle",
                                            "TextOrientation": "RotateToPlayer",
                                            "TextScale": 1,
                                            "ShowInteractionTextAtCursorPos": 0,
                                            "ScalePromptOffsetWithEntity": 0,
                                            "PromptStyle": "PromptAndText",
                                            "OverrideControlHintDescription": 0,
                                            "InteractionPromptScale": 1,
                                            "InteractionPromptLabelVerticalOffset": 70,
                                            "InteractionPromptBound": "TopBoundingBoxZSurface",
                                            "UseHorizontalDistance": 0,
                                            "MaxCursorScreenDistance": 2,
                                            "ShowInnerThoughtsOffScreen": 0,
                                            "OnlySelectableInLookDir": 0,
                                            "Interactions": [
                                                {
                                                    "DisplayName": "",
                                                    "__DisplayName": "@LOC_EMPTY",
                                                    "IsPrimary": 1,
                                                    "Interaction": {
                                                        "value": "SSharedInteractionParams[A56D]"
                                                    }
                                                },
                                                {
                                                    "DisplayName": "",
                                                    "__DisplayName": "@LOC_EMPTY",
                                                    "IsPrimary": 0,
                                                    "Interaction": {
                                                        "value": "SSharedInteractionParams[A570]"
                                                    }
                                                },
                                                {
                                                    "DisplayName": "",
                                                    "__DisplayName": "@LOC_EMPTY",
                                                    "IsPrimary": 0,
                                                    "Interaction": {
                                                        "value": "SSharedInteractionParams[A571]"
                                                    }
                                                },
                                                {
                                                    "DisplayName": "",
                                                    "__DisplayName": "@LOC_EMPTY",
                                                    "IsPrimary": 0,
                                                    "Interaction": {
                                                        "value": "SSharedInteractionParams[A572]"
                                                    }
                                                },
                                                {
                                                    "DisplayName": "Loot",
                                                    "__DisplayName": "@interaction_loot",
                                                    "IsPrimary": 0,
                                                    "Interaction": {
                                                        "value": "SSharedInteractionParams[A573]"
                                                    }
                                                }
                                            ],
                                            "Tags": [
                                                {
                                                    "value": "c7663132-a612-4b0c-bc5b-144ac55e267e"
                                                },
                                                {
                                                    "value": "ce1c13f1-a8ba-49cf-a025-89475ea07000"
                                                }
                                            ],
                                            "Offset": {
                                                "Rotation": {
                                                    "x": 0,
                                                    "y": 0,
                                                    "z": 0
                                                },
                                                "Position": {
                                                    "x": 0,
                                                    "y": 0,
                                                    "z": 0
                                                }
                                            },
                                            "InteractionPromptOffset": {
                                                "Rotation": {
                                                    "x": 0,
                                                    "y": 0,
                                                    "z": 0
                                                },
                                                "Position": {
                                                    "x": 0,
                                                    "y": 0,
                                                    "z": 0
                                                }
                                            },
                                            "AngleConstraint": {
                                                "angleRange": 181,
                                                "viewAngleLimit": 110,
                                                "forwardDirOffset": {
                                                    "x": 0,
                                                    "y": 0,
                                                    "z": 0
                                                }
                                            }
                                        }
                                    }
                                },
                                {
                                    "StateName": "Settled",
                                    "Interactions": [
                                        {
                                            "Interaction": {
                                                "value": "SSharedInteractionParams[A574]"
                                            }
                                        },
                                        {
                                            "Interaction": {
                                                "value": "SSharedInteractionParams[A577]"
                                            }
                                        },
                                        {
                                            "Interaction": {
                                                "value": "SSharedInteractionParams[A578]"
                                            }
                                        },
                                        {
                                            "Interaction": {
                                                "value": "SSharedInteractionParams[A579]"
                                            }
                                        }
                                    ],
                                    "interactionPoints": {
                                        "SInteractionPointParams": {
                                            "HelperName": "HighlightOnRayHitEntity",
                                            "FirstInteractionPrimary": 0,
                                            "UseHelperLocation": 0,
                                            "ApplyToEntireSkeleton": 0,
                                            "longRangeIP": 0,
                                            "Radius": 2,
                                            "ShowHighlight": 1,
                                            "HighlightOnRayHitEntity": 1,
                                            "TextJustification": "Middle",
                                            "TextOrientation": "RotateToPlayer",
                                            "TextScale": 1,
                                            "ShowInteractionTextAtCursorPos": 0,
                                            "ScalePromptOffsetWithEntity": 0,
                                            "PromptStyle": "PromptAndText",
                                            "OverrideControlHintDescription": 0,
                                            "InteractionPromptScale": 1,
                                            "InteractionPromptLabelVerticalOffset": 70,
                                            "InteractionPromptBound": "TopBoundingBoxZSurface",
                                            "UseHorizontalDistance": 0,
                                            "MaxCursorScreenDistance": 2,
                                            "ShowInnerThoughtsOffScreen": 0,
                                            "OnlySelectableInLookDir": 0,
                                            "Interactions": [
                                                {
                                                    "DisplayName": "",
                                                    "__DisplayName": "@LOC_EMPTY",
                                                    "IsPrimary": 1,
                                                    "Interaction": {
                                                        "value": "SSharedInteractionParams[A574]"
                                                    }
                                                },
                                                {
                                                    "DisplayName": "",
                                                    "__DisplayName": "@LOC_EMPTY",
                                                    "IsPrimary": 0,
                                                    "Interaction": {
                                                        "value": "SSharedInteractionParams[A577]"
                                                    }
                                                },
                                                {
                                                    "DisplayName": "",
                                                    "__DisplayName": "@LOC_EMPTY",
                                                    "IsPrimary": 0,
                                                    "Interaction": {
                                                        "value": "SSharedInteractionParams[A578]"
                                                    }
                                                },
                                                {
                                                    "DisplayName": "",
                                                    "__DisplayName": "@LOC_EMPTY",
                                                    "IsPrimary": 0,
                                                    "Interaction": {
                                                        "value": "SSharedInteractionParams[A579]"
                                                    }
                                                },
                                                {
                                                    "DisplayName": "Loot",
                                                    "__DisplayName": "@interaction_loot",
                                                    "IsPrimary": 0,
                                                    "Interaction": {
                                                        "value": "SSharedInteractionParams[A57A]"
                                                    }
                                                }
                                            ],
                                            "Tags": [
                                                {
                                                    "value": "c7663132-a612-4b0c-bc5b-144ac55e267e"
                                                },
                                                {
                                                    "value": "ce1c13f1-a8ba-49cf-a025-89475ea07000"
                                                }
                                            ],
                                            "Offset": {
                                                "Rotation": {
                                                    "x": 0,
                                                    "y": 0,
                                                    "z": 0
                                                },
                                                "Position": {
                                                    "x": 0,
                                                    "y": 0,
                                                    "z": 0
                                                }
                                            },
                                            "InteractionPromptOffset": {
                                                "Rotation": {
                                                    "x": 0,
                                                    "y": 0,
                                                    "z": 0
                                                },
                                                "Position": {
                                                    "x": 0,
                                                    "y": 0,
                                                    "z": 0
                                                }
                                            },
                                            "AngleConstraint": {
                                                "angleRange": 181,
                                                "viewAngleLimit": 110,
                                                "forwardDirOffset": {
                                                    "x": 0,
                                                    "y": 0,
                                                    "z": 0
                                                }
                                            }
                                        }
                                    }
                                },
                                {
                                    "StateName": "Carried",
                                    "Interactions": [
                                        {
                                            "Interaction": {
                                                "value": "SSharedInteractionParams[A576]"
                                            }
                                        },
                                        {
                                            "Interaction": {
                                                "value": "SSharedInteractionParams[A575]"
                                            }
                                        },
                                        {
                                            "Interaction": {
                                                "value": "SSharedInteractionParams[A577]"
                                            }
                                        },
                                        {
                                            "Interaction": {
                                                "value": "SSharedInteractionParams[A578]"
                                            }
                                        }
                                    ],
                                    "interactionPoints": {
                                        "SInteractionPointParams": {
                                            "HelperName": "HighlightOnRayHitEntity",
                                            "FirstInteractionPrimary": 0,
                                            "UseHelperLocation": 0,
                                            "ApplyToEntireSkeleton": 0,
                                            "longRangeIP": 0,
                                            "Radius": 2,
                                            "ShowHighlight": 1,
                                            "HighlightOnRayHitEntity": 1,
                                            "TextJustification": "Middle",
                                            "TextOrientation": "RotateToPlayer",
                                            "TextScale": 1,
                                            "ShowInteractionTextAtCursorPos": 0,
                                            "ScalePromptOffsetWithEntity": 0,
                                            "PromptStyle": "PromptAndText",
                                            "OverrideControlHintDescription": 0,
                                            "InteractionPromptScale": 1,
                                            "InteractionPromptLabelVerticalOffset": 70,
                                            "InteractionPromptBound": "TopBoundingBoxZSurface",
                                            "UseHorizontalDistance": 0,
                                            "MaxCursorScreenDistance": 2,
                                            "ShowInnerThoughtsOffScreen": 0,
                                            "OnlySelectableInLookDir": 0,
                                            "Interactions": [
                                                {
                                                    "DisplayName": "",
                                                    "__DisplayName": "@LOC_EMPTY",
                                                    "IsPrimary": 1,
                                                    "Interaction": {
                                                        "value": "SSharedInteractionParams[A574]"
                                                    }
                                                },
                                                {
                                                    "DisplayName": "",
                                                    "__DisplayName": "@LOC_EMPTY",
                                                    "IsPrimary": 0,
                                                    "Interaction": {
                                                        "value": "SSharedInteractionParams[A577]"
                                                    }
                                                },
                                                {
                                                    "DisplayName": "",
                                                    "__DisplayName": "@LOC_EMPTY",
                                                    "IsPrimary": 0,
                                                    "Interaction": {
                                                        "value": "SSharedInteractionParams[A578]"
                                                    }
                                                },
                                                {
                                                    "DisplayName": "",
                                                    "__DisplayName": "@LOC_EMPTY",
                                                    "IsPrimary": 0,
                                                    "Interaction": {
                                                        "value": "SSharedInteractionParams[A579]"
                                                    }
                                                },
                                                {
                                                    "DisplayName": "Loot",
                                                    "__DisplayName": "@interaction_loot",
                                                    "IsPrimary": 0,
                                                    "Interaction": {
                                                        "value": "SSharedInteractionParams[A57A]"
                                                    }
                                                }
                                            ],
                                            "Tags": [
                                                {
                                                    "value": "c7663132-a612-4b0c-bc5b-144ac55e267e"
                                                },
                                                {
                                                    "value": "ce1c13f1-a8ba-49cf-a025-89475ea07000"
                                                }
                                            ],
                                            "Offset": {
                                                "Rotation": {
                                                    "x": 0,
                                                    "y": 0,
                                                    "z": 0
                                                },
                                                "Position": {
                                                    "x": 0,
                                                    "y": 0,
                                                    "z": 0
                                                }
                                            },
                                            "InteractionPromptOffset": {
                                                "Rotation": {
                                                    "x": 0,
                                                    "y": 0,
                                                    "z": 0
                                                },
                                                "Position": {
                                                    "x": 0,
                                                    "y": 0,
                                                    "z": 0
                                                }
                                            },
                                            "AngleConstraint": {
                                                "angleRange": 181,
                                                "viewAngleLimit": 110,
                                                "forwardDirOffset": {
                                                    "x": 0,
                                                    "y": 0,
                                                    "z": 0
                                                }
                                            }
                                        }
                                    }
                                }
                            ]
                        },
                        {
                            "StateTypeName": "Main",
                            "bindingsMethod": "Name",
                            "asopReset": 0,
                            "networkAuthority": "Server",
                            "States": [
                                {
                                    "StateName": "Dropped"
                                },
                                {
                                    "StateName": "Stored",
                                    "Interactions": [
                                        {
                                            "Interaction": {
                                                "value": "SSharedInteractionParams[A574]"
                                            }
                                        },
                                        {
                                            "Interaction": {
                                                "value": "SSharedInteractionParams[A575]"
                                            }
                                        },
                                        {
                                            "Interaction": {
                                                "value": "SSharedInteractionParams[A578]"
                                            }
                                        },
                                        {
                                            "Interaction": {
                                                "value": "SSharedInteractionParams[A579]"
                                            }
                                        }
                                    ],
                                    "interactionPoints": {
                                        "SInteractionPointParams": {
                                            "HelperName": "Spine3",
                                            "FirstInteractionPrimary": 0,
                                            "UseHelperLocation": 0,
                                            "ApplyToEntireSkeleton": 0,
                                            "longRangeIP": 0,
                                            "Radius": 2,
                                            "ShowHighlight": 1,
                                            "HighlightOnRayHitEntity": 0,
                                            "TextJustification": "Middle",
                                            "TextOrientation": "RotateToPlayer",
                                            "TextScale": 1,
                                            "ShowInteractionTextAtCursorPos": 0,
                                            "ScalePromptOffsetWithEntity": 0,
                                            "PromptStyle": "PromptAndText",
                                            "OverrideControlHintDescription": 0,
                                            "InteractionPromptScale": 1,
                                            "InteractionPromptLabelVerticalOffset": 70,
                                            "InteractionPromptBound": "EntityRoot",
                                            "UseHorizontalDistance": 0,
                                            "MaxCursorScreenDistance": 2,
                                            "ShowInnerThoughtsOffScreen": 0,
                                            "OnlySelectableInLookDir": 0,
                                            "Interactions": [
                                                {
                                                    "DisplayName": "",
                                                    "__DisplayName": "@LOC_EMPTY",
                                                    "IsPrimary": 0,
                                                    "Interaction": {
                                                        "value": "SSharedInteractionParams[A574]"
                                                    }
                                                },
                                                {
                                                    "DisplayName": "",
                                                    "__DisplayName": "@LOC_EMPTY",
                                                    "IsPrimary": 0,
                                                    "Interaction": {
                                                        "value": "SSharedInteractionParams[A575]"
                                                    }
                                                },
                                                {
                                                    "DisplayName": "",
                                                    "__DisplayName": "@LOC_EMPTY",
                                                    "IsPrimary": 0,
                                                    "Interaction": {
                                                        "value": "SSharedInteractionParams[A576]"
                                                    }
                                                },
                                                {
                                                    "DisplayName": "",
                                                    "__DisplayName": "@LOC_EMPTY",
                                                    "IsPrimary": 0,
                                                    "Interaction": {
                                                        "value": "SSharedInteractionParams[A577]"
                                                    }
                                                },
                                                {
                                                    "DisplayName": "",
                                                    "__DisplayName": "@LOC_EMPTY",
                                                    "IsPrimary": 0,
                                                    "Interaction": {
                                                        "value": "SSharedInteractionParams[A578]"
                                                    }
                                                },
                                                {
                                                    "DisplayName": "Open",
                                                    "__DisplayName": "@interaction_open",
                                                    "IsPrimary": 0,
                                                    "Interaction": {
                                                        "value": "SSharedInteractionParams[A579]"
                                                    }
                                                },
                                                {
                                                    "DisplayName": "Loot",
                                                    "__DisplayName": "@interaction_loot",
                                                    "IsPrimary": 0,
                                                    "Interaction": {
                                                        "value": "SSharedInteractionParams[A57A]"
                                                    }
                                                }
                                            ],
                                            "Tags": [
                                                {
                                                    "value": "95b959c6-fb00-4d63-b062-a36d86b66128"
                                                },
                                                {
                                                    "value": "d8a79162-cc7b-4f0d-9445-c25530cf1588"
                                                }
                                            ],
                                            "Offset": {
                                                "Rotation": {
                                                    "x": 0,
                                                    "y": 0,
                                                    "z": 0
                                                },
                                                "Position": {
                                                    "x": 0,
                                                    "y": 0,
                                                    "z": 0
                                                }
                                            },
                                            "InteractionPromptOffset": {
                                                "Rotation": {
                                                    "x": 0,
                                                    "y": 0,
                                                    "z": 0
                                                },
                                                "Position": {
                                                    "x": 0,
                                                    "y": 0,
                                                    "z": 0
                                                }
                                            },
                                            "AngleConstraint": {
                                                "angleRange": 181,
                                                "viewAngleLimit": 110,
                                                "forwardDirOffset": {
                                                    "x": 0,
                                                    "y": 0,
                                                    "z": 0
                                                }
                                            }
                                        }
                                    }
                                }
                            ],
                            "StateModifiers": {
                                "SKioskInteractionStateModifier": {
                                    "onKioskInteractionOpen": {
                                        "value": "SInteractionState[9A3D]"
                                    },
                                    "onKioskInteractionClose": {
                                        "value": "SInteractionState[9A3C]"
                                    }
                                }
                            }
                        }
                    ]
                },
                "EntityPhysicalAudioParams": {
                    "minimumImpulseContinuous": 3,
                    "minimumImpulseTransient": 3,
                    "minimumVelocityNoImpulse": 3,
                    "slideThreshold": 0.04,
                    "rollThreshold": 0.04,
                    "momentumScale": 1,
                    "rollVelocityScale": 1,
                    "useAABBCentre": 0,
                    "oneShotTag": "0d401f6c-38a4-4c52-bb02-26059dd8d98a",
                    "oneShotCooldown": 0.2,
                    "dragOnly": 0,
                    "collisionTriggers": {
                        "PhysicalAudioCollisionTrigger": {
                            "oneShotMinPlayTime": 0.25,
                            "attachToObject": 0,
                            "trigger": {
                                "audioTrigger": "Play_PHOB_Physics_Objects_Generic_Inherited_Impact_01"
                            }
                        }
                    },
                    "slideStartTrigger": {
                        "audioTrigger": "Play_PHOB_Physics_Objects_Generic_Inherited_Sliding_01"
                    },
                    "rollStartTrigger": {
                        "audioTrigger": "Play_PHOB_Physics_Objects_Generic_Inherited_Rolling_01"
                    },
                    "movementStartTrigger": {
                        "audioTrigger": "Play_PHOB_Physics_Objects_Generic_Inherited_Movement_01"
                    },
                    "pickupTrigger": {
                        "audioTrigger": "Play_PHOB_Physics_Objects_Generic_Inherited_Pickup_01"
                    },
                    "dropTrigger": {
                        "audioTrigger": "Play_PHOB_Physics_Objects_Generic_Inherited_Drop_01"
                    },
                    "placeTrigger": {
                        "audioTrigger": "Play_PHOB_Physics_Objects_Generic_Inherited_Place_01"
                    },
                    "rtpcSlideVelocity": {
                        "rtpc": "PhysicalAudio_Velocity"
                    },
                    "rtpcMassSelf": {
                        "rtpc": "PhysicalAudio_MassSelf"
                    },
                    "rtpcMassOther": {
                        "rtpc": "PhysicalAudio_MassOther"
                    },
                    "rtpcDampening": {
                        "rtpc": "PhysicalAudio_Damping"
                    },
                    "rtpcRollVelocity": {
                        "rtpc": "PhysicalAudio_RollVelocity"
                    },
                    "rtpcHealth": {
                        "rtpc": "PhysicalAudio_Health"
                    },
                    "rtpcMovement": {
                        "rtpc": "PhysicalAudio_Movement"
                    },
                    "rtpcRotation": {
                        "rtpc": "PhysicalAudio_Rotation"
                    },
                    "rtpcTimeSinceLastOneshot": {
                        "rtpc": "PhysicalAudio_TimeSinceLastOneshot"
                    },
                    "rtpcMomentum": {
                        "rtpc": "PhysicalAudio_Momentum"
                    },
                    "rtpcCarried": {
                        "rtpc": "PhysicalAudio_CarryState"
                    }
                },
                "SEntityAudioControllerParams": {
                    "audioControllerEntityType": "None",
                    "randomSeedCount": 1,
                    "fullLODDistance": 9000,
                    "fullToLowLODDistance": 9050,
                    "offToLowLODDistance": 10000,
                    "offLODDistance": 10050,
                    "occlusionAttenuationScaler": 0.5
                },
                "SCItemMobiGlasProviderParams": {
                    "appTransitionTime": 0.5,
                    "onlyAllowUserInteractions": 0,
                    "startOpen": 0,
                    "closeTime": 1,
                    "defaultInstalledApps": {
                        "mobiGlasDefaultAppEntry": {
                            "defaultMobiGlasApp": "59b720fa-c9ae-4dca-8103-d76cda21fb7e",
                            "defaultAppData": {
                                "Reference": {
                                    "value": "f6f3a883-181b-4e5a-bcf6-e258ac8c0781"
                                }
                            }
                        }
                    }
                },
                "UIBuildingBlocksEntityComponentParams": {
                    "enableFullScreenMouse": 0,
                    "defaultStyle": "b1be5fa8-90ea-4555-83ba-4011b91e0d47",
                    "layers": {
                        "BuildingBlocksLayer": {
                            "layerName": "Main",
                            "renderTarget": "All",
                            "defaultView": {
                                "value": "BuildingBlocksView[0846]"
                            },
                            "views": {
                                "BuildingBlocksView": {
                                    "name": "Main",
                                    "component": {
                                        "canvas": "8183f248-7099-485d-a799-8a03c32d2e72",
                                        "isSystemViewInstance": 0,
                                        "canvasInstantiationMode": "RootDeferred"
                                    }
                                }
                            }
                        }
                    }
                },
                "UIBindingsConsumerEntityComponentParams": {
                    "linkToPort": 0
                },
                "UIBindingsInteractionsComponentParams": {
                    "interactionDistance": 50
                },
                "UserVariablesComponentParams": {
                    "AlwaysUseDefaultValues": 0,
                    "ints": [
                        {
                            "name": "Manufacturer",
                            "defaultValue": 2
                        },
                        {
                            "name": "selectedDataIndex",
                            "defaultValue": 0
                        },
                        {
                            "name": "selectedApp",
                            "defaultValue": 0
                        }
                    ],
                    "bools": [
                        {
                            "name": "SortDropdownExpanded",
                            "defaultValue": 0
                        },
                        {
                            "name": "weaponRackDropdownExpanded",
                            "defaultValue": 0
                        },
                        {
                            "name": "filterDropdownExpanded",
                            "defaultValue": 0
                        }
                    ]
                },
                "UISimpleRenderNodeEntityComponentParams": {
                    "minimumBounds": 1,
                    "materialName": "materials/default_ui.mtl",
                    "sortDistance": 0.1,
                    "fixedScaleMin": 0,
                    "fixedScaleMax": 0,
                    "cardStageRadius": 0.5,
                    "flattenBehavior": "FlattenAs2D",
                    "interference": 0
                },
                "UIRenderToTextureEntityComponentParams": {
                    "directRenderStage": "None",
                    "hideRenderNodeOnUnload": 0,
                    "aspectRatioOverride": 0,
                    "interactionDistance": 2,
                    "transparentListDepthBias": 0,
                    "renderFlashBeforeCamera": 0,
                    "fieldOfView": 90,
                    "nearClip": 0.02,
                    "farClip": 65536,
                    "renderType": "FORWARD",
                    "pickableCollision": "Opaque",
                    "runtimeImageSource": "UserInterface",
                    "runtimeImageToAggregate": 0
                },
                "UIOwnerEntityComponentParams": {
                    "startOpen": 1,
                    "areScreens3D": 0,
                    "areSounds3D": 0,
                    "hasActions": 0,
                    "element": "235bfc85-aa63-4fd5-b5d1-821fb3522a39",
                    "domainName": "global",
                    "loadDistance": 8,
                    "movieAutoPlay": 0,
                    "loopMovie": 0,
                    "forceFlashColourCorrection": 1,
                    "ignoreTrackviewUnloadRequests": 0,
                    "reflectLocalStateMachine": 1,
                    "reflectLinkedStateMachines": 0
                }
            },
            "ClassName": "Carryable_1H_SQ_Datapad_Fluff_Orb_GenericGang_003",
            "__type": "Misc"
        }
    },
    "Item": {
        "className": "Carryable_1H_SQ_Datapad_Fluff_Orb_GenericGang_003",
        "reference": "9b8d6f07-8eb2-4760-a62f-72b363169aec",
        "itemName": "carryable_1h_sq_datapad_fluff_orb_genericgang_003",
        "type": "Misc",
        "subType": "UNDEFINED",
        "size": 1,
        "grade": 1,
        "name": "<= PLACEHOLDER =>",
        "tags": "Tablet",
        "entity_tags": [
            "5e11a544-7fea-4160-b2bf-98c6cf9ee9df",
            "00ead468-9073-485b-a6df-ca6b94053603",
            "4def30aa-4ed2-404a-9439-6713f246f1e3",
            "05e263e6-d3be-40dd-a89d-6ff7d1d8a3ac"
        ],
        "entity_tag_map": [
            {
                "tag": "5e11a544-7fea-4160-b2bf-98c6cf9ee9df",
                "name": "1H"
            },
            {
                "tag": "00ead468-9073-485b-a6df-ca6b94053603",
                "name": "ActionArea"
            },
            {
                "tag": "4def30aa-4ed2-404a-9439-6713f246f1e3",
                "name": "Tablet"
            },
            {
                "tag": "05e263e6-d3be-40dd-a89d-6ff7d1d8a3ac",
                "name": "Orbageddon"
            }
        ],
        "stdItem": {
            "UUID": "9b8d6f07-8eb2-4760-a62f-72b363169aec",
            "ClassName": "Carryable_1H_SQ_Datapad_Fluff_Orb_GenericGang_003",
            "Size": 1,
            "Grade": 1,
            "Width": 0.2498,
            "Height": 0.0204,
            "Length": 0.3017,
            "InventoryOccupancy": {
                "Dimensions": {
                    "Width": 0.25,
                    "Length": 0.3,
                    "Height": 0.02
                },
                "UIDimensions": {
                    "Width": 0.75,
                    "Length": 0.75,
                    "Height": 0.75
                },
                "Volume": {
                    "SCU": 0.0012,
                    "SCUConverted": 1200,
                    "Unit": "\u00b5SCU"
                }
            },
            "Mass": 0.25,
            "Type": "Misc.UNDEFINED",
            "Name": "<= PLACEHOLDER =>",
            "Description": "",
            "DescriptionText": "",
            "Manufacturer": {
                "Name": "Unknown Manufacturer",
                "Code": "UNKN",
                "UUID": "00000000-0000-0000-0000-000000000000"
            },
            "Tags": [
                "Tablet"
            ],
            "DimensionOverrides": {
                "Width": 0.75,
                "Length": 0.75,
                "Height": 0.75,
                "Volume": 0.216
            },
            "Interactions": [
                "Carry",
                "Drop",
                "Inspect",
                "Place",
                "Store",
                "Drink"
            ]
        }
    }
}