{
  "UUID": "156405d4-8819-4d76-b300-2dd18ff1abd0",
  "ClassName": "counter_display_mod_end_0038x01x01_02Ports",
  "Size": 1,
  "Grade": 1,
  "Type": "ShopDisplay.UNDEFINED",
  "Name": "counter_display_mod_end_0038x01x01_02Ports",
  "Width": 0.15,
  "Height": 0.15,
  "Length": 0.15,
  "Volume": 1E-06,
  "Ports": [
    {
      "PortName": "Inner_Port_01",
      "Size": 1,
      "Types": [
        "WeaponAttachment"
      ],
      "Flags": [
        "tableDisplay"
      ]
    },
    {
      "PortName": "Top_Port_1",
      "Size": 1,
      "Types": [
        "WeaponPersonal.Gadget"
      ],
      "Flags": [
        "tableDisplay"
      ]
    }
  ]
}