{
  "notForRelease": true,
  "owner": "8f84d8f2-5f01-4b56-8529-e9861aa5f2fe",
  "missionModule": "Libs/Subsumption/Missions/PU/Missions/Salvage/SalvageContractor.xml",
  "title": "@cfp_salvage_nodanger_title_001",
  "titleHUD": "@cfp_salvage_nodanger_title_001",
  "description": "@cfp_salvage_nodanger_desc_001",
  "missionGiver": "Citizens for Prosperity",
  "commsChannelName": "@LOC_UNINITIALIZED",
  "type": "655cbe6e-19df-4757-8a05-a4cbd2bae78f",
  "localityAvailable": "9a5db783-28de-42fc-97b8-4e9adb34d561",
  "locationMissionAvailable": "00000000-0000-0000-0000-000000000000",
  "initiallyActive": true,
  "notifyOnAvailable": false,
  "showAsOffer": false,
  "missionBuyInAmount": 20000,
  "refundBuyInOnWithdraw": 0,
  "hasCompleteButton": true,
  "handlesAbandonRequest": false,
  "missionModulePerPlayer": 1,
  "maxInstances": -1,
  "maxPlayersPerInstance": 1,
  "maxInstancesPerPlayer": 1,
  "canBeShared": true,
  "onceOnly": false,
  "tutorial": false,
  "displayAlliedMarkers": true,
  "availableInPrison": false,
  "failIfSentToPrison": true,
  "failIfBecameCriminal": false,
  "failIfLeavePrison": false,
  "requestOnly": false,
  "respawnTime": 10,
  "respawnTimeVariation": 2.0,
  "instanceHasLifeTime": false,
  "showLifeTimeInMobiGlas": true,
  "instanceLifeTime": 30,
  "instanceLifeTimeVariation": 2.0,
  "canReacceptAfterAbandoning": true,
  "abandonedCooldownTime": 1,
  "abandonedCooldownTimeVariation": 1.0,
  "canReacceptAfterFailing": true,
  "hasPersonalCooldown": false,
  "personalCooldownTime": 1,
  "personalCooldownTimeVariation": 1.0,
  "moduleHandlesOwnShutdown": true,
  "linkedMission": "00000000-0000-0000-0000-000000000000",
  "lawfulMission": true,
  "missionGiverRecord": "00000000-0000-0000-0000-000000000000",
  "invitationMission": "00000000-0000-0000-0000-000000000000",
  "missionGiverFragmentTags": "",
  "associatedMissions": [],
  "missionReward": {
    "reward": 0,
    "max": 0,
    "plusBonusses": 0,
    "currencyType": "UEC",
    "reputationBonus": "00000000-0000-0000-0000-000000000000"
  },
  "missionResultReputationRewards": [
    {
      "reputationAmounts": [
        {
          "reputationScope": "f340b011-c40c-4229-b9c1-ce6a3eb1df77",
          "reward": "21f73b65-3e45-4453-afba-d0713a239da0"
        },
        {
          "reputationScope": "9116b87c-46fe-4cf6-8c1b-b55f1b4bf5a1",
          "reward": "21f73b65-3e45-4453-afba-d0713a239da0"
        }
      ]
    },
    {
      "reputationAmounts": []
    },
    {
      "reputationAmounts": [
        {
          "reputationScope": "f340b011-c40c-4229-b9c1-ce6a3eb1df77",
          "reward": "5a59f6f6-245f-4e43-a08b-8b67e38286a7"
        },
        {
          "reputationScope": "9116b87c-46fe-4cf6-8c1b-b55f1b4bf5a1",
          "reward": "5a59f6f6-245f-4e43-a08b-8b67e38286a7"
        }
      ]
    },
    {
      "reputationAmounts": [
        {
          "reputationScope": "f340b011-c40c-4229-b9c1-ce6a3eb1df77",
          "reward": "5a59f6f6-245f-4e43-a08b-8b67e38286a7"
        },
        {
          "reputationScope": "9116b87c-46fe-4cf6-8c1b-b55f1b4bf5a1",
          "reward": "5a59f6f6-245f-4e43-a08b-8b67e38286a7"
        }
      ]
    },
    {
      "reputationAmounts": []
    }
  ],
  "missionDeadline": {
    "missionCompletionTime": 0,
    "missionAutoEnd": false,
    "missionResultAfterTimerEnd": "Failed",
    "remainingTimeToShowTimer": 0,
    "missionEndReason": "@LOC_EMPTY"
  },
  "completionTags": {
    "tags": []
  },
  "modifiers": {
    "modifiers": [
      {
        "clearanceToken": "b757b8b6-ce57-41ce-8a99-bed24b7eb681",
        "locationProperty": "null",
        "__polymorphicType": "MissionModifier_SecurityClearance"
      }
    ]
  },
  "missionTags": [],
  "reputationPrerequisites": {
    "wantedLevelJurisdictionOverride": "00000000-0000-0000-0000-000000000000",
    "wantedLevel": {
      "minValue": 0,
      "maxValue": 5
    }
  },
  "requiredMissions": [],
  "requiredCompletedMissionTags": {},
  "ClassName": "PU_SalvageContractor_NoDanger_Pyro_CFP_Easy_Pyro5",
  "__ref": "f5b8bb47-1d41-4858-ac06-8cde6a1902a3",
  "__type": "MissionBrokerEntry"
}